mongo_automation_only/__init__.py
mongo_automation_only/mongodb_crud.py
mongo_only-0.0.3.dist-info/LICENSE
mongo_only-0.0.3.dist-info/METADATA
mongo_only-0.0.3.dist-info/WHEEL
mongo_only-0.0.3.dist-info/top_level.txt
mongo_only-0.0.3.dist-info/RECORD
